MANIFEST.in
README.txt
setup.cfg
setup.py
c2/__init__.py
c2.patch.effectivedateforlisting.egg-info/PKG-INFO
c2.patch.effectivedateforlisting.egg-info/SOURCES.txt
c2.patch.effectivedateforlisting.egg-info/dependency_links.txt
c2.patch.effectivedateforlisting.egg-info/entry_points.txt
c2.patch.effectivedateforlisting.egg-info/namespace_packages.txt
c2.patch.effectivedateforlisting.egg-info/not-zip-safe
c2.patch.effectivedateforlisting.egg-info/requires.txt
c2.patch.effectivedateforlisting.egg-info/top_level.txt
c2/patch/__init__.py
c2/patch/effectivedateforlisting/__init__.py
c2/patch/effectivedateforlisting/configure.zcml
c2/patch/effectivedateforlisting/monkey.py
c2/patch/effectivedateforlisting/version.txt
c2/patch/effectivedateforlisting/profiles/default/metadata.xml
c2/patch/effectivedateforlisting/profiles/default/skins.xml
c2/patch/effectivedateforlisting/skins/effectivedateforlisting/getFolderContents.py
c2/patch/effectivedateforlisting/tests/__init__.py
c2/patch/effectivedateforlisting/tests/base.py
c2/patch/effectivedateforlisting/tests/test_setup.py
docs/HISTORY.txt
docs/INSTALL.txt
docs/LICENSE.GPL
docs/LICENSE.txt