Metadata-Version: 1.0
Name: c2.patch.effectivedateforlisting
Version: 1.0a1
Summary: This patch product is to show effective contents on folder contents.
Home-page: http://www.cmscom.jp
Author: Manabu TERADA
Author-email: terada@cmscom.jp
License: GPL
Keywords: plone patch folder_listing effectivedate
Platform: UNKNOWN
Classifier: Framework :: Plone
Classifier: Programming Language :: Python
Classifier: Topic :: Software Development :: Libraries :: Python Modules
